README.rst
setup.py
briekit/__init__.py
briekit/brie_factor.py
briekit.egg-info/PKG-INFO
briekit.egg-info/SOURCES.txt
briekit.egg-info/dependency_links.txt
briekit.egg-info/entry_points.txt
briekit.egg-info/requires.txt
briekit.egg-info/top_level.txt
briekit/events/__init__.py
briekit/events/defineEvents.py
briekit/events/event_filter.py
briekit/events/event_maker.py
briekit/events/parseTables.py
briekit/utils/__init__.py
briekit/utils/fasta_utils.py
briekit/utils/gtf_utils.py
briekit/utils/sam_utils.py
sashimi_plot/Sashimi.py
sashimi_plot/__init__.py
sashimi_plot/plot.py
sashimi_plot/sashimi_plot.py
sashimi_plot/plot_utils/__init__.py
sashimi_plot/plot_utils/plot_gene.py
sashimi_plot/plot_utils/plot_settings.py
sashimi_plot/plot_utils/plotting.py
sashimi_plot/plot_utils/samples_plotter.py