Metadata-Version: 1.0
Name: briekit
Version: 0.2.2
Summary: BRIE-kit: Preprocessing tool kit of BRIE in splicing analysis
Home-page: https://github.com/huangyh09/briekit
Author: Yuanhua Huang
Author-email: yuanhua@ebi.ac.uk
License: Apache-2.0
Keywords: Splicing events annotation,Sequence features
Platform: UNKNOWN
